oligo_designer_toolsuite_ai_filters/__init__.py
oligo_designer_toolsuite_ai_filters/_version.py
oligo_designer_toolsuite_ai_filters/api/__init__.py
oligo_designer_toolsuite_ai_filters/api/_api_base.py
oligo_designer_toolsuite_ai_filters/api/_api_hybridization_probability.py
oligo_designer_toolsuite_ai_filters/hybridization_probability/__init__.py
oligo_designer_toolsuite_ai_filters/hybridization_probability/_dataset.py
oligo_designer_toolsuite_ai_filters/hybridization_probability/_models.py
oligo_designer_toolsuite_ai_filters/hybridization_probability/generate_artificial_dataset.py
oligo_designer_toolsuite_ai_filters/hybridization_probability/generate_real_dataset.py
oligo_designer_toolsuite_ai_filters/hybridization_probability/train_model.py
oligo_designer_toolsuite_ai_filters/pretrained_models/hybridization_probability.pt
oligo_designer_toolsuite_ai_filters-0.0.4.dist-info/METADATA
oligo_designer_toolsuite_ai_filters-0.0.4.dist-info/WHEEL
oligo_designer_toolsuite_ai_filters-0.0.4.dist-info/top_level.txt
oligo_designer_toolsuite_ai_filters-0.0.4.dist-info/RECORD
