Metadata-Version: 2.1
Name: oligo-designer-toolsuite-ai-filters
Version: 0.0.4
Summary: AI plug-ins for the Oligo Designer Toolsuite package
Author-email: Francesco Campi <francesco.campi@helmholtz-munich.de>, Lisa Barros de Andrade e Sousa <lisa.barros.andrade.sousa@gmail.com>
Maintainer-email: Francesco Campi <francesco.campi@helmholtz-munich.de>
Project-URL: repository, https://github.com/HelmholtzAI-Consultants-Munich/oligo-designer-toolsuite-AI-filters
Keywords: bioinformatics,probes,oligo nucleotides,probe design,oligo design
Classifier: Programming Language :: Python :: 3
Classifier: License :: OSI Approved :: MIT License
Classifier: Operating System :: OS Independent
Requires-Dist: torch
Requires-Dist: seaborn
Requires-Dist: pandas
Requires-Dist: biopython
